coresight_sdk/__init__.py
coresight_sdk/client.py
coresight_sdk/exceptions.py
coresight_sdk/feedback.py
coresight_sdk/messages.py
coresight_sdk/projects.py
coresight_sdk/subscriptions.py
coresight_sdk/threads.py
coresight_sdk/users.py
coresight_sdk/utils.py
coresight_sdk-1.0.2.dist-info/METADATA
coresight_sdk-1.0.2.dist-info/WHEEL
coresight_sdk-1.0.2.dist-info/RECORD
