Metadata-Version: 2.3
Name: coresight_sdk
Version: 1.0.2
Summary: Python SDK for the CoreSight API
License: MIT
Author: Daniel García
Author-email: info@iamdgarcia.com
Requires-Python: >=3.9,<3.13
Classifier: License :: OSI Approved :: MIT License
Classifier: Programming Language :: Python :: 3
Classifier: Programming Language :: Python :: 3.9
Classifier: Programming Language :: Python :: 3.10
Classifier: Programming Language :: Python :: 3.11
Classifier: Programming Language :: Python :: 3.12
Requires-Dist: requests (>=2.20,<3.0)
